setFTs/__init__.py
setFTs/datasets.py
setFTs/fast.cpython-39-x86_64-linux-gnu.so
setFTs/minmax.py
setFTs/plotting.py
setFTs/setfunctions.py
setFTs/transformations.py
setFTs/utils.py
setFTs/data/bitcount_10.csv
setFTs/data/bzip2d_10.csv
setFTs/data/bzip2e_10.csv
setFTs/data/jpeg_c10.csv
setFTs/data/jpeg_d10.csv
setFTs/data/susan_c10.csv
setFTs/data/susan_e10.csv
setFTs/data/susan_e_1_GCC_10_1024.csv
setFTs/data/susan_s10.csv
setFTs/data/sensor_placement/Berkeley.csv
setFTs/data/sensor_placement/California.csv
setFTs/data/sensor_placement/Rain.csv
setFTs-0.0.1.1.dist-info/LICENSE
setFTs-0.0.1.1.dist-info/METADATA
setFTs-0.0.1.1.dist-info/WHEEL
setFTs-0.0.1.1.dist-info/top_level.txt
setFTs-0.0.1.1.dist-info/RECORD
