Metadata-Version: 2.1
Name: setFTs
Version: 0.0.1.1
Summary: A collection of Discrete Set Fourier Transformation Algorithms
Author: Simon Ebner
Author-email: ebners@ethz.ch
License: UNKNOWN
Platform: UNKNOWN
License-File: LICENSE
